{
  "type": "Feature",
  "properties": {
    "gn:admin1_code":"7.0",
    "gn:asciiname":"Casole",
    "gn:country_code":"SM",
    "gn:dem":507,
    "gn:feature_class":"P",
    "gn:feature_code":"PPL",
    "gn:name":"Casole",
    "gn:population":0,
    "gn:timezone":"Europe/San_Marino",
    "iso:country":"SM",
    "wof:name":"Casole",
    "wof:placetype":"locality"
},
  "geometry": {"coordinates":[12.44442,43.91697],"type":"Point"}
}