{
  "type": "Feature",
  "properties": {
    "gn:admin1_code":"9.0",
    "gn:asciiname":"Fiorina",
    "gn:country_code":"SM",
    "gn:dem":218,
    "gn:feature_class":"P",
    "gn:feature_code":"PPL",
    "gn:name":"Fiorina",
    "gn:population":0,
    "gn:timezone":"Europe/San_Marino",
    "iso:country":"SM",
    "wof:name":"Fiorina",
    "wof:placetype":"locality"
},
  "geometry": {"coordinates":[12.47686,43.95798],"type":"Point"}
}