{
  "type": "Feature",
  "properties": {
    "gn:admin1_code":"9.0",
    "gn:asciiname":"Fiorina",
    "gn:country_code":"SM",
    "gn:dem":218,
    "gn:feature_class":"P",
    "gn:feature_code":"PPL",
    "gn:name":"Fiorina",
    "gn:population":0,
    "gn:timezone":"Europe/San_Marino",
    "iso:country":"SM",
    "name:ceb_x_preferred":[
        "Fiorina"
    ],
    "name:ita_x_preferred":[
        "Fiorina"
    ],
    "name:ltz_x_preferred":[
        "Fiorina"
    ],
    "name:sco_x_preferred":[
        "Fiorina"
    ],
    "name:spa_x_preferred":[
        "Fiorina"
    ],
    "name:ukr_x_preferred":[
        "\u0424\u0456\u043e\u0440\u0456\u043d\u0430"
    ],
    "wof:name":"Fiorina",
    "wof:placetype":"locality"
},
  "geometry": {"coordinates":[12.47686,43.95798],"type":"Point"}
}